{"rCode":"0","rMessage":"게시글 작성 시, \"파트너스 활동을 통해 일정액의 수수료를 제공받을 수 있음\"을 기재하셔야 합니다","data":[{"productId":27613130,"productName":"탐사수, 2L, 12개","productPrice":6840,"productImage":"https://static.coupangcdn.com/image/product/image/vendoritem/2019/03/04/3213757282/456ca43b-ffe6-46ef-b793-d787986a9e52.jpg","productUrl":"https://link.coupang.com/re/AFFSDP?lptag=AF9416635&pageKey=27613130&itemId=109846121&vendorItemId=3213757282&traceid=V0-113-b860fd2b23f3b002","categoryName":"헬스/건강식품","keyword":"헬스/건강식품","rank":1,"isRocket":true,"isFreeShipping":false},{"productId":27613130,"productName":"탐사수, 500ml, 40개","productPrice":8490,"productImage":"https://static.coupangcdn.com/image/retail/images/1045307148511-59e2ad7d-ad27-46d9-83b8-e62dfc7a22d7.jpg","productUrl":"https://link.coupang.com/re/AFFSDP?lptag=AF9416635&pageKey=27613130&itemId=109845886&vendorItemId=3213756530&traceid=V0-113-b860fd2b23f3b002","categoryName":"헬스/건강식품","keyword":"헬스/건강식품","rank":2,"isRocket":true,"isFreeShipping":false},{"productId":5625704601,"productName":"탐사수 무라벨, 2L, 24개입","productPrice":11290,"productImage":"https://static.coupangcdn.com/image/retail/images/7609662521933713-0d7870de-5716-43c5-a3f5-22f7a34f3a43.jpg","productUrl":"https://link.coupang.com/re/AFFSDP?lptag=AF9416635&pageKey=5625704601&itemId=11696984031&vendorItemId=79548063314&traceid=V0-113-3c520143be477c84","categoryName":"헬스/건강식품","keyword":"헬스/건강식품","rank":3,"isRocket":true,"isFreeShipping":false},{"productId":5585425593,"productName":"제주삼다수, 2L, 12개","productPrice":11760,"productImage":"https://static.coupangcdn.com/image/retail/images/985508834192757-97e47bf1-07ba-43f5-875a-18e09828741e.jpg","productUrl":"https://link.coupang.com/re/AFFSDP?lptag=AF9416635&pageKey=5585425593&itemId=9127023704&vendorItemId=70798313484&traceid=V0-113-abf71007c1bbec2a","categoryName":"헬스/건강식품","keyword":"헬스/건강식품","rank":4,"isRocket":true,"isFreeShipping":false},{"productId":1271064981,"productName":"곰곰 무항생제 신선한 대란, 30구","productPrice":8180,"productImage":"https://static.coupangcdn.com/image/retail/images/339902015030616-cb87422f-4fda-44cf-a111-a518381dc91d.jpg","productUrl":"https://link.coupang.com/re/AFFSDP?lptag=AF9416635&pageKey=1271064981&itemId=2275730724&vendorItemId=70272921582&traceid=V0-113-5e7ea65e5d0510be","categoryName":"헬스/건강식품","keyword":"헬스/건강식품","rank":5,"isRocket":true,"isFreeShipping":false},{"productId":5647481827,"productName":"제주삼다수 그린, 12개, 2L","productPrice":11760,"productImage":"https://static.coupangcdn.com/image/retail/images/984553174710887-19b20f38-aa24-4b16-a827-ddba7796e1f2.jpg","productUrl":"https://link.coupang.com/re/AFFSDP?lptag=AF9416635&pageKey=5647481827&itemId=11133888548&vendorItemId=76490822316&traceid=V0-113-b105b4669b6afd74","categoryName":"헬스/건강식품","keyword":"헬스/건강식품","rank":6,"isRocket":true,"isFreeShipping":false},{"productId":172073083,"productName":"수원축협 무항생제 인증 대란 30구, 1560g, 1개","productPrice":8590,"productImage":"https://static.coupangcdn.com/image/retail/images/2018/12/28/9/0/2706d072-91f8-40d1-b609-bac824deeeed.jpg","productUrl":"https://link.coupang.com/re/AFFSDP?lptag=AF9416635&pageKey=172073083&itemId=491955480&vendorItemId=4246128952&traceid=V0-113-448c4b0e26f94ae4","categoryName":"헬스/건강식품","keyword":"헬스/건강식품","rank":7,"isRocket":true,"isFreeShipping":false},{"productId":5647481827,"productName":"제주삼다수 그린, 24개, 2L","productPrice":23520,"productImage":"https://static.coupangcdn.com/image/retail/images/72788633809924-c23b361e-3162-4abd-8fd6-69a41675e0f1.jpg","productUrl":"https://link.coupang.com/re/AFFSDP?lptag=AF9416635&pageKey=5647481827&itemId=9231892331&vendorItemId=76517595828&traceid=V0-113-b105b4669b6afd74","categoryName":"헬스/건강식품","keyword":"헬스/건강식품","rank":8,"isRocket":true,"isFreeShipping":false},{"productId":1959587814,"productName":"코멧 일회용 마스크, 100개입, 1개, 블랙","productPrice":11990,"productImage":"https://static.coupangcdn.com/image/retail/images/187050618654682-9bfaeba6-4b57-4050-9022-36290dbb6a33.jpg","productUrl":"https://link.coupang.com/re/AFFSDP?lptag=AF9416635&pageKey=1959587814&itemId=6990259694&vendorItemId=74282560062&traceid=V0-113-4e1f65f86bd3059f","categoryName":"헬스/건강식품","keyword":"헬스/건강식품","rank":9,"isRocket":true,"isFreeShipping":false},{"productId":1756477824,"productName":"코멧 일회용 마스크, 100개입, 1개, 화이트","productPrice":11990,"productImage":"https://static.coupangcdn.com/image/retail/images/187063362359519-4e19d0af-c9f0-4dfe-b566-f5d742c6ee1b.jpg","productUrl":"https://link.coupang.com/re/AFFSDP?lptag=AF9416635&pageKey=1756477824&itemId=6990259829&vendorItemId=74282560185&traceid=V0-113-35fd01ea4676626f","categoryName":"헬스/건강식품","keyword":"헬스/건강식품","rank":10,"isRocket":true,"isFreeShipping":false},{"productId":5585425593,"productName":"제주삼다수, 500ml, 40개","productPrice":16370,"productImage":"https://static.coupangcdn.com/image/retail/images/77035642063104-a25310da-8461-4d47-b79b-d47c7d59dea6.jpg","productUrl":"https://link.coupang.com/re/AFFSDP?lptag=AF9416635&pageKey=5585425593&itemId=2808742845&vendorItemId=70798313475&traceid=V0-113-abf71007c1bbec2a","categoryName":"헬스/건강식품","keyword":"헬스/건강식품","rank":11,"isRocket":true,"isFreeShipping":false},{"productId":5585425593,"productName":"제주삼다수, 2L, 24개","productPrice":23520,"productImage":"https://static.coupangcdn.com/image/retail/images/597195908017512-e5a3f864-9d3d-45a9-99df-6b3f57410b7f.jpg","productUrl":"https://link.coupang.com/re/AFFSDP?lptag=AF9416635&pageKey=5585425593&itemId=3423820284&vendorItemId=71503222724&traceid=V0-113-abf71007c1bbec2a","categoryName":"헬스/건강식품","keyword":"헬스/건강식품","rank":12,"isRocket":true,"isFreeShipping":false},{"productId":1271113288,"productName":"곰곰 무항생제 신선한 특란, 30구","productPrice":8980,"productImage":"https://static.coupangcdn.com/image/retail/images/338669665322720-4c27cf14-bd16-4419-88a3-09148c440962.jpg","productUrl":"https://link.coupang.com/re/AFFSDP?lptag=AF9416635&pageKey=1271113288&itemId=2275793934&vendorItemId=70272921457&traceid=V0-113-0826521277c3a554","categoryName":"헬스/건강식품","keyword":"헬스/건강식품","rank":13,"isRocket":true,"isFreeShipping":false},{"productId":1153527125,"productName":"수원축협 무항생제 특란, 1800g, 1개","productPrice":8990,"productImage":"https://static.coupangcdn.com/image/retail/images/2020/01/07/16/7/63fc49b7-e304-4354-b226-cfb4ca4f41fb.jpg","productUrl":"https://link.coupang.com/re/AFFSDP?lptag=AF9416635&pageKey=1153527125&itemId=2128359252&vendorItemId=70126904793&traceid=V0-113-c778854939b9fbd9","categoryName":"헬스/건강식품","keyword":"헬스/건강식품","rank":14,"isRocket":true,"isFreeShipping":false},{"productId":4866946618,"productName":"매일 소화가 잘되는 우유, 190ml, 24개","productPrice":15180,"productImage":"https://static.coupangcdn.com/image/retail/images/3277494721530-8d0f7786-e250-4bb7-a131-f706fdeb0aef.jpg","productUrl":"https://link.coupang.com/re/AFFSDP?lptag=AF9416635&pageKey=4866946618&itemId=6318956874&vendorItemId=3025163213&traceid=V0-113-d629da1e07c75772","categoryName":"헬스/건강식품","keyword":"헬스/건강식품","rank":15,"isRocket":true,"isFreeShipping":false},{"productId":156688977,"productName":"다향오리 1등급 훈제 오리 슬라이스, 600g, 1개","productPrice":11760,"productImage":"https://static.coupangcdn.com/image/retail/images/107202630603864-9300fd85-73c5-45bf-9bcf-83ee1a15a28d.jpg","productUrl":"https://link.coupang.com/re/AFFSDP?lptag=AF9416635&pageKey=156688977&itemId=451180258&vendorItemId=4117267681&traceid=V0-113-5066b6f8b6fb6380","categoryName":"헬스/건강식품","keyword":"헬스/건강식품","rank":16,"isRocket":true,"isFreeShipping":false},{"productId":1074470755,"productName":"국내산 햇양파, 3kg, 1봉","productPrice":8460,"productImage":"https://static.coupangcdn.com/image/retail/images/49244623787243-bdd50e78-3848-44f3-87b5-5dec38f04324.jpg","productUrl":"https://link.coupang.com/re/AFFSDP?lptag=AF9416635&pageKey=1074470755&itemId=2024034712&vendorItemId=70023661066&traceid=V0-113-faa1a5ef3bec40bf","categoryName":"헬스/건강식품","keyword":"헬스/건강식품","rank":17,"isRocket":true,"isFreeShipping":false},{"productId":27613130,"productName":"탐사수, 1L, 24개","productPrice":10890,"productImage":"https://static.coupangcdn.com/image/retail/images/8312630257199135-d9d6445b-f448-4914-8461-6b2b9605eeaa.jpg","productUrl":"https://link.coupang.com/re/AFFSDP?lptag=AF9416635&pageKey=27613130&itemId=109845991&vendorItemId=3289410352&traceid=V0-113-b860fd2b23f3b002","categoryName":"헬스/건강식품","keyword":"헬스/건강식품","rank":18,"isRocket":true,"isFreeShipping":false},{"productId":6203740135,"productName":"가야산 천년수 무라벨, 2L, 24개","productPrice":10290,"productImage":"https://static.coupangcdn.com/image/retail/images/2497202434064267-fb56a7c5-f21b-4f6e-95c1-856569cf3c90.jpg","productUrl":"https://link.coupang.com/re/AFFSDP?lptag=AF9416635&pageKey=6203740135&itemId=12325672441&vendorItemId=71686199406&traceid=V0-113-e1f43126e0d3ce57","categoryName":"헬스/건강식품","keyword":"헬스/건강식품","rank":19,"isRocket":true,"isFreeShipping":false},{"productId":5625704601,"productName":"탐사수 무라벨, 500ml, 60개입","productPrice":11890,"productImage":"https://static.coupangcdn.com/image/retail/images/8490946390630062-860cc30c-bf13-4328-ab25-52d81b215aa2.jpg","productUrl":"https://link.coupang.com/re/AFFSDP?lptag=AF9416635&pageKey=5625704601&itemId=11696970903&vendorItemId=79547658934&traceid=V0-113-3c520143be477c84","categoryName":"헬스/건강식품","keyword":"헬스/건강식품","rank":20,"isRocket":true,"isFreeShipping":false},{"productId":4744789493,"productName":"스테비아 스윗토 방울토마토, 1.2kg, 1팩","productPrice":17080,"productImage":"https://static.coupangcdn.com/image/retail/images/6817304430420781-dc8ef306-584f-40d4-9ba9-ce0b1b12dad6.jpg","productUrl":"https://link.coupang.com/re/AFFSDP?lptag=AF9416635&pageKey=4744789493&itemId=6032995407&vendorItemId=73330579108&traceid=V0-113-2195a851bf0297b4","categoryName":"헬스/건강식품","keyword":"헬스/건강식품","rank":21,"isRocket":true,"isFreeShipping":false},{"productId":5456053369,"productName":"국내산 양파, 5kg, 1개","productPrice":8250,"productImage":"https://static.coupangcdn.com/image/retail/images/5892067031719-7c17f7d9-85bf-4606-8879-59faefae79aa.jpg","productUrl":"https://link.coupang.com/re/AFFSDP?lptag=AF9416635&pageKey=5456053369&itemId=8339724411&vendorItemId=75627534291&traceid=V0-113-9d1c68782edfa549","categoryName":"헬스/건강식품","keyword":"헬스/건강식품","rank":22,"isRocket":true,"isFreeShipping":false},{"productId":2195614135,"productName":"한스웰 한마음 일회용 황사 마스크 대형 KF94, 1개입, 100개","productPrice":17000,"productImage":"https://static.coupangcdn.com/image/retail/images/337793990663600-4045ece6-e817-475a-8210-3fd8c2a17f56.jpg","productUrl":"https://link.coupang.com/re/AFFSDP?lptag=AF9416635&pageKey=2195614135&itemId=8374800688&vendorItemId=71620251613&traceid=V0-113-3a86ba308f217c0a","categoryName":"헬스/건강식품","keyword":"헬스/건강식품","rank":23,"isRocket":true,"isFreeShipping":false},{"productId":270205855,"productName":"더건강한 샌드위치햄, 100g, 3개","productPrice":5920,"productImage":"https://static.coupangcdn.com/image/retail/images/5697808742221110-c039ab50-5dfc-436f-a0ca-85cc1139e63a.jpg","productUrl":"https://link.coupang.com/re/AFFSDP?lptag=AF9416635&pageKey=270205855&itemId=848459293&vendorItemId=5157084243&traceid=V0-113-9f9280ceb6cb8361","categoryName":"헬스/건강식품","keyword":"헬스/건강식품","rank":24,"isRocket":true,"isFreeShipping":false},{"productId":6098365781,"productName":"종근당건강 락토핏 생유산균 골드 80, 160g, 3개","productPrice":44100,"productImage":"https://static.coupangcdn.com/image/retail/images/1010356697169658-18ff19f0-bd61-49a0-9322-437dd4f9c323.jpg","productUrl":"https://link.coupang.com/re/AFFSDP?lptag=AF9416635&pageKey=6098365781&itemId=622626985&vendorItemId=4635121437&traceid=V0-113-c695d42f1e2a91ac","categoryName":"헬스/건강식품","keyword":"헬스/건강식품","rank":25,"isRocket":true,"isFreeShipping":false},{"productId":293308540,"productName":"탐사수, 500ml, 60개","productPrice":10950,"productImage":"https://static.coupangcdn.com/image/retail/images/164711284228015-f1aaffe6-c6ae-44dc-8ae0-0461995ceff6.jpg","productUrl":"https://link.coupang.com/re/AFFSDP?lptag=AF9416635&pageKey=293308540&itemId=926267525&vendorItemId=5302016221&traceid=V0-113-89266386732d1dc2","categoryName":"헬스/건강식품","keyword":"헬스/건강식품","rank":26,"isRocket":true,"isFreeShipping":false},{"productId":4697181000,"productName":"완숙토마토, 2kg, 1개","productPrice":8800,"productImage":"https://static.coupangcdn.com/image/retail/images/2173841899147126-a9e0ec7a-97c9-4ec2-9151-fe1e846615ee.jpg","productUrl":"https://link.coupang.com/re/AFFSDP?lptag=AF9416635&pageKey=4697181000&itemId=5911957948&vendorItemId=73210036901&traceid=V0-113-f26ced760395ffab","categoryName":"헬스/건강식품","keyword":"헬스/건강식품","rank":27,"isRocket":true,"isFreeShipping":false},{"productId":115750443,"productName":"가농 금계란 매일 만나는 1+등급 특란 15구, 900g, 1개","productPrice":7690,"productImage":"https://static.coupangcdn.com/image/retail/images/7354037612024-40b366d8-e04b-498c-83f5-f2c76955fa79.jpg","productUrl":"https://link.coupang.com/re/AFFSDP?lptag=AF9416635&pageKey=115750443&itemId=351199290&vendorItemId=3855802737&traceid=V0-113-2d89045a053405cc","categoryName":"헬스/건강식품","keyword":"헬스/건강식품","rank":28,"isRocket":true,"isFreeShipping":false},{"productId":293308540,"productName":"탐사수, 2L, 24개","productPrice":11690,"productImage":"https://static.coupangcdn.com/image/retail/images/873394256992-7e874da2-d555-4f7d-b5ff-c098b3775d40.jpg","productUrl":"https://link.coupang.com/re/AFFSDP?lptag=AF9416635&pageKey=293308540&itemId=926269831&vendorItemId=5302019285&traceid=V0-113-89266386732d1dc2","categoryName":"헬스/건강식품","keyword":"헬스/건강식품","rank":29,"isRocket":true,"isFreeShipping":false},{"productId":6203740135,"productName":"가야산천년수 무라벨 생수, 2L, 30개","productPrice":12780,"productImage":"https://static.coupangcdn.com/image/retail/images/2956692496996238-b5bce10e-abf1-45ab-9e71-5be7610302d3.jpg","productUrl":"https://link.coupang.com/re/AFFSDP?lptag=AF9416635&pageKey=6203740135&itemId=12325659222&vendorItemId=75794756217&traceid=V0-113-e1f43126e0d3ce57","categoryName":"헬스/건강식품","keyword":"헬스/건강식품","rank":30,"isRocket":true,"isFreeShipping":false},{"productId":597741,"productName":"고려은단 비타민C 1000, 180정, 1개","productPrice":16110,"productImage":"https://static.coupangcdn.com/image/retail/images/17731399300739-9ed7906a-76b8-475c-b468-4e1555a6d571.jpg","productUrl":"https://link.coupang.com/re/AFFSDP?lptag=AF9416635&pageKey=597741&itemId=11404739747&vendorItemId=3000235591&traceid=V0-113-0d4e0802acc87885","categoryName":"헬스/건강식품","keyword":"헬스/건강식품","rank":31,"isRocket":true,"isFreeShipping":false},{"productId":4869850477,"productName":"탐사 KF94 방역마스크 새부리형 2단접이 50p (5매입 지퍼백 10개), 대형","productPrice":15290,"productImage":"https://static.coupangcdn.com/image/retail/images/510946399354470-c91e9b57-88ac-4828-8f7d-b3011f40c330.jpg","productUrl":"https://link.coupang.com/re/AFFSDP?lptag=AF9416635&pageKey=4869850477&itemId=6326081431&vendorItemId=73621504982&traceid=V0-113-d0a99d01a9e6ff62","categoryName":"헬스/건강식품","keyword":"헬스/건강식품","rank":32,"isRocket":true,"isFreeShipping":false},{"productId":5580450200,"productName":"트레비 라임 ECO, 350ml, 20개","productPrice":16990,"productImage":"https://static.coupangcdn.com/image/retail/images/2021/05/27/14/3/c8e03ca6-8946-42b4-af39-f43805f30efc.jpg","productUrl":"https://link.coupang.com/re/AFFSDP?lptag=AF9416635&pageKey=5580450200&itemId=8916733616&vendorItemId=76203338434&traceid=V0-113-ec7ebbd5156cff0c","categoryName":"헬스/건강식품","keyword":"헬스/건강식품","rank":33,"isRocket":true,"isFreeShipping":false},{"productId":1445352464,"productName":"무항생제 인증 가농 금계란 1+등급 왕란, 1020g, 1개","productPrice":6600,"productImage":"https://static.coupangcdn.com/image/retail/images/1651133991019954-e4ead365-ec27-4932-ad30-06c6bd83541f.jpg","productUrl":"https://link.coupang.com/re/AFFSDP?lptag=AF9416635&pageKey=1445352464&itemId=2490591778&vendorItemId=70483793754&traceid=V0-113-9cceb6a65d39ebe1","categoryName":"헬스/건강식품","keyword":"헬스/건강식품","rank":34,"isRocket":true,"isFreeShipping":false},{"productId":266254917,"productName":"곰곰 광천 도시락김, 32개","productPrice":7970,"productImage":"https://static.coupangcdn.com/image/retail/images/8020250270528-10ac8b65-0c86-45a1-a733-2d57c2cdc98b.jpg","productUrl":"https://link.coupang.com/re/AFFSDP?lptag=AF9416635&pageKey=266254917&itemId=834542714&vendorItemId=5124578637&traceid=V0-113-7eba649f055d7e5d","categoryName":"헬스/건강식품","keyword":"헬스/건강식품","rank":35,"isRocket":true,"isFreeShipping":false},{"productId":1308889924,"productName":"곰곰 슈레드 모짜렐라 피자치즈, 1kg, 1개","productPrice":9240,"productImage":"https://static.coupangcdn.com/image/retail/images/82989828437051-13f73e44-c6cb-4b62-97c4-a5fb595d0811.jpg","productUrl":"https://link.coupang.com/re/AFFSDP?lptag=AF9416635&pageKey=1308889924&itemId=2325255337&vendorItemId=70321898123&traceid=V0-113-c037a2e31581c988","categoryName":"헬스/건강식품","keyword":"헬스/건강식품","rank":36,"isRocket":true,"isFreeShipping":false},{"productId":1255642405,"productName":"곰곰 토마토, 1kg, 1팩","productPrice":6990,"productImage":"https://static.coupangcdn.com/image/retail/images/12930340760122-f93e59a5-738a-43bf-9bfc-2b67eab3fb08.jpeg","productUrl":"https://link.coupang.com/re/AFFSDP?lptag=AF9416635&pageKey=1255642405&itemId=2256020213&vendorItemId=70253344760&traceid=V0-113-3435263a1bb8171b","categoryName":"헬스/건강식품","keyword":"헬스/건강식품","rank":37,"isRocket":true,"isFreeShipping":false},{"productId":5647481827,"productName":"제주삼다수 그린, 40개, 500ml","productPrice":16930,"productImage":"https://static.coupangcdn.com/image/retail/images/67638885182352-8c3d11b2-22cd-459b-bb85-11d99a131afc.png","productUrl":"https://link.coupang.com/re/AFFSDP?lptag=AF9416635&pageKey=5647481827&itemId=9231892303&vendorItemId=76517595767&traceid=V0-113-b105b4669b6afd74","categoryName":"헬스/건강식품","keyword":"헬스/건강식품","rank":38,"isRocket":true,"isFreeShipping":false},{"productId":2042132,"productName":"동원 라이트 스탠다드 참치, 85g, 12개","productPrice":15900,"productImage":"https://static.coupangcdn.com/image/retail/images/12871751529171-4423dd3b-c919-4ca6-b841-66fc9076c437.jpg","productUrl":"https://link.coupang.com/re/AFFSDP?lptag=AF9416635&pageKey=2042132&itemId=9176537&vendorItemId=3013141169&traceid=V0-113-2b815ccce2b76a7d","categoryName":"헬스/건강식품","keyword":"헬스/건강식품","rank":39,"isRocket":true,"isFreeShipping":false},{"productId":4650530853,"productName":"곰곰 국내산 딸기, 500g, 1팩","productPrice":13800,"productImage":"https://static.coupangcdn.com/image/retail/images/8775026544366858-b54baf1f-1687-416d-8a3b-69f52101d21a.jpg","productUrl":"https://link.coupang.com/re/AFFSDP?lptag=AF9416635&pageKey=4650530853&itemId=5797807689&vendorItemId=73096293638&traceid=V0-113-068fe75311cfe467","categoryName":"헬스/건강식품","keyword":"헬스/건강식품","rank":40,"isRocket":true,"isFreeShipping":false},{"productId":324788226,"productName":"홈플래닛 초음파 가습기 4L, HL1-1001D1(반투명 물탱크/무드등 사용 가능)","productPrice":30090,"productImage":"https://static.coupangcdn.com/image/retail/images/1543969731160341-53ca96b5-707b-48e9-9a55-647251b0e9e6.png","productUrl":"https://link.coupang.com/re/AFFSDP?lptag=AF9416635&pageKey=324788226&itemId=3801974770&vendorItemId=71786943698&traceid=V0-113-3edcd694e7edecd4","categoryName":"헬스/건강식품","keyword":"헬스/건강식품","rank":41,"isRocket":true,"isFreeShipping":false},{"productId":131222787,"productName":"웅진 빅토리아 청포도 스파클링 음료, 500ml, 20개","productPrice":10530,"productImage":"https://static.coupangcdn.com/image/product/image/vendoritem/2018/11/12/3938771464/f637e89f-0725-4f32-898f-0be0d09980b7.jpg","productUrl":"https://link.coupang.com/re/AFFSDP?lptag=AF9416635&pageKey=131222787&itemId=386242196&vendorItemId=3938771464&traceid=V0-113-ea25f780f04b7f94","categoryName":"헬스/건강식품","keyword":"헬스/건강식품","rank":42,"isRocket":true,"isFreeShipping":false},{"productId":1175646750,"productName":"아이클리어 루테인지아잔틴, 30캡슐, 3박스","productPrice":23070,"productImage":"https://static.coupangcdn.com/image/rs_quotation_api/cr9apl1b/624777eccf724d13bff05214e616019c.jpg","productUrl":"https://link.coupang.com/re/AFFSDP?lptag=AF9416635&pageKey=1175646750&itemId=2154401346&vendorItemId=77582829254&traceid=V0-113-1535445f532b7fcd","categoryName":"헬스/건강식품","keyword":"헬스/건강식품","rank":43,"isRocket":true,"isFreeShipping":false},{"productId":5647481827,"productName":"제주삼다수 그린, 60개, 500ml","productPrice":25780,"productImage":"https://static.coupangcdn.com/image/retail/images/1801448985629224-768c8604-a328-4b9e-99b0-678c7aa62263.jpg","productUrl":"https://link.coupang.com/re/AFFSDP?lptag=AF9416635&pageKey=5647481827&itemId=9231892299&vendorItemId=76517595751&traceid=V0-113-b105b4669b6afd74","categoryName":"헬스/건강식품","keyword":"헬스/건강식품","rank":44,"isRocket":true,"isFreeShipping":false},{"productId":1473796614,"productName":"곰곰 호주산 소고기 앞다리살 국거리용 300g (냉장), 1개","productPrice":9190,"productImage":"https://static.coupangcdn.com/image/retail/images/7789812867576679-b9c97692-d200-4bc3-b701-9159865eff58.jpg","productUrl":"https://link.coupang.com/re/AFFSDP?lptag=AF9416635&pageKey=1473796614&itemId=2532934918&vendorItemId=70525675924&traceid=V0-113-23a1d54e19c7f3ce","categoryName":"헬스/건강식품","keyword":"헬스/건강식품","rank":45,"isRocket":true,"isFreeShipping":false},{"productId":297630338,"productName":"웅진 빅토리아 탄산수 플레인, 500ml, 20개","productPrice":10700,"productImage":"https://static.coupangcdn.com/image/retail/images/254993088133454-bc644017-865e-4d1f-9219-660ad89e9214.jpg","productUrl":"https://link.coupang.com/re/AFFSDP?lptag=AF9416635&pageKey=297630338&itemId=702126471&vendorItemId=3008867464&traceid=V0-113-fa377215d866ef4c","categoryName":"헬스/건강식품","keyword":"헬스/건강식품","rank":46,"isRocket":true,"isFreeShipping":false},{"productId":5101484777,"productName":"탐사 KF94 마스크 레귤러핏 (개별포장), 대형, 1매, 100개","productPrice":21690,"productImage":"https://static.coupangcdn.com/image/retail/images/56267917617161-11da93b8-6c2e-416d-8163-00004e900613.jpg","productUrl":"https://link.coupang.com/re/AFFSDP?lptag=AF9416635&pageKey=5101484777&itemId=6950069661&vendorItemId=74242530774&traceid=V0-113-3f43a0fa2546b45a","categoryName":"헬스/건강식품","keyword":"헬스/건강식품","rank":47,"isRocket":true,"isFreeShipping":false},{"productId":1194639177,"productName":"곰곰 반숙란 (냉장), 50g, 20구","productPrice":10900,"productImage":"https://static.coupangcdn.com/image/retail/images/2646071061018768-021e4cde-d7c5-47e3-a925-01183a921604.jpg","productUrl":"https://link.coupang.com/re/AFFSDP?lptag=AF9416635&pageKey=1194639177&itemId=2177439743&vendorItemId=70175514691&traceid=V0-113-597e3f51b07d091b","categoryName":"헬스/건강식품","keyword":"헬스/건강식품","rank":48,"isRocket":true,"isFreeShipping":false},{"productId":1267767150,"productName":"목우촌 국내산 소고기 양지 세절 국거리용 (냉장), 300g, 1개","productPrice":15900,"productImage":"https://static.coupangcdn.com/image/retail/images/2807872764465125-3faee9a3-e764-486d-87ea-82553c276845.jpg","productUrl":"https://link.coupang.com/re/AFFSDP?lptag=AF9416635&pageKey=1267767150&itemId=2271396043&vendorItemId=70268609273&traceid=V0-113-ccc734209075100c","categoryName":"헬스/건강식품","keyword":"헬스/건강식품","rank":49,"isRocket":true,"isFreeShipping":false},{"productId":4869850477,"productName":"탐사 KF94 방역마스크 새부리형 2단접이 50p (5매입 지퍼백 10개), 소형","productPrice":13900,"productImage":"https://static.coupangcdn.com/image/retail/images/1676705060869810-0c0e0fb4-6e62-4037-bdfb-d8f977ced483.jpg","productUrl":"https://link.coupang.com/re/AFFSDP?lptag=AF9416635&pageKey=4869850477&itemId=6326081435&vendorItemId=73621504991&traceid=V0-113-d0a99d01a9e6ff62","categoryName":"헬스/건강식품","keyword":"헬스/건강식품","rank":50,"isRocket":true,"isFreeShipping":false},{"productId":5647481827,"productName":"제주삼다수 그린, 18개, 2L","productPrice":17640,"productImage":"https://static.coupangcdn.com/image/retail/images/576314632990574-313b0707-7062-4f49-a444-eef1b5a0b074.jpg","productUrl":"https://link.coupang.com/re/AFFSDP?lptag=AF9416635&pageKey=5647481827&itemId=9231892317&vendorItemId=76517595808&traceid=V0-113-b105b4669b6afd74","categoryName":"헬스/건강식품","keyword":"헬스/건강식품","rank":51,"isRocket":true,"isFreeShipping":false},{"productId":68148071,"productName":"탐사 스파클링 플레인 탄산수, 500ml, 20개","productPrice":9900,"productImage":"https://static.coupangcdn.com/image/retail/images/171624124729720-21da10b3-92fa-4dc2-af28-06ecb23745a7.jpg","productUrl":"https://link.coupang.com/re/AFFSDP?lptag=AF9416635&pageKey=68148071&itemId=535951702&vendorItemId=4398875781&traceid=V0-113-39951cfdccad2a6f","categoryName":"헬스/건강식품","keyword":"헬스/건강식품","rank":52,"isRocket":true,"isFreeShipping":false},{"productId":5625737250,"productName":"탐사 KF94 마스크 레귤러핏 (10매 지퍼백*10개), 블랙, 10매, 10개","productPrice":19090,"productImage":"https://static.coupangcdn.com/image/retail/images/1028239174730291-19a61555-3ccb-40cc-81ab-b8a9f0e0a95d.jpg","productUrl":"https://link.coupang.com/re/AFFSDP?lptag=AF9416635&pageKey=5625737250&itemId=9134030605&vendorItemId=76420034375&traceid=V0-113-485e73f76cfd8adf","categoryName":"헬스/건강식품","keyword":"헬스/건강식품","rank":53,"isRocket":true,"isFreeShipping":false},{"productId":5585425593,"productName":"제주삼다수, 2L, 18개","productPrice":17640,"productImage":"https://static.coupangcdn.com/image/retail/images/30880001340772-8e0afaab-a408-4e97-bd0e-cc81071578dd.jpg","productUrl":"https://link.coupang.com/re/AFFSDP?lptag=AF9416635&pageKey=5585425593&itemId=9127023698&vendorItemId=70798319518&traceid=V0-113-abf71007c1bbec2a","categoryName":"헬스/건강식품","keyword":"헬스/건강식품","rank":54,"isRocket":true,"isFreeShipping":false},{"productId":1357560685,"productName":"아워홈 지리산수 핑크, 500ml, 40개","productPrice":7960,"productImage":"https://static.coupangcdn.com/image/retail/images/2020/06/24/18/1/78e6972b-b806-43ba-8205-d82d05376f5a.jpg","productUrl":"https://link.coupang.com/re/AFFSDP?lptag=AF9416635&pageKey=1357560685&itemId=5747705235&vendorItemId=70956436363&traceid=V0-113-fafe80139f625949","categoryName":"헬스/건강식품","keyword":"헬스/건강식품","rank":55,"isRocket":true,"isFreeShipping":false},{"productId":5101426628,"productName":"탐사 KF-AD 비말차단 마스크 대형, 100개입, 1개","productPrice":14090,"productImage":"https://static.coupangcdn.com/image/retail/images/1287411785056-5f2dd333-924f-4f54-8c48-79f9d931c7cd.jpg","productUrl":"https://link.coupang.com/re/AFFSDP?lptag=AF9416635&pageKey=5101426628&itemId=6949975526&vendorItemId=74242437121&traceid=V0-113-dce4a4047b9f6cbc","categoryName":"헬스/건강식품","keyword":"헬스/건강식품","rank":56,"isRocket":true,"isFreeShipping":false},{"productId":266254917,"productName":"곰곰 광천 도시락김, 64개입","productPrice":12590,"productImage":"https://static.coupangcdn.com/image/retail/images/187262082363887-147552b2-1dc2-4f46-b82a-d5309b266b0e.jpg","productUrl":"https://link.coupang.com/re/AFFSDP?lptag=AF9416635&pageKey=266254917&itemId=6506504132&vendorItemId=73800734497&traceid=V0-113-7eba649f055d7e5d","categoryName":"헬스/건강식품","keyword":"헬스/건강식품","rank":57,"isRocket":true,"isFreeShipping":false},{"productId":5585425593,"productName":"제주삼다수, 500ml, 60개","productPrice":24550,"productImage":"https://static.coupangcdn.com/image/retail/images/62399869319388-c2005720-f670-411d-a4d7-df2e959bee8d.jpg","productUrl":"https://link.coupang.com/re/AFFSDP?lptag=AF9416635&pageKey=5585425593&itemId=4152850019&vendorItemId=72136709491&traceid=V0-113-abf71007c1bbec2a","categoryName":"헬스/건강식품","keyword":"헬스/건강식품","rank":58,"isRocket":true,"isFreeShipping":false},{"productId":6101896267,"productName":"곰곰 달콤한 스테비아 대추방울토마토, 1kg, 1팩","productPrice":14220,"productImage":"https://static.coupangcdn.com/image/retail/images/7873900259404961-a524e429-7b4c-4603-a4b8-749e8309f9c4.jpg","productUrl":"https://link.coupang.com/re/AFFSDP?lptag=AF9416635&pageKey=6101896267&itemId=11440236121&vendorItemId=78715723909&traceid=V0-113-4a5e06e6eeea506b","categoryName":"헬스/건강식품","keyword":"헬스/건강식품","rank":59,"isRocket":true,"isFreeShipping":false},{"productId":227331483,"productName":"하림 IFF 닭가슴살 (냉동), 2kg, 1개","productPrice":13640,"productImage":"https://static.coupangcdn.com/image/retail/images/241120252118987-8cae9932-7345-4439-bcdf-2de5376a25c9.jpg","productUrl":"https://link.coupang.com/re/AFFSDP?lptag=AF9416635&pageKey=227331483&itemId=720227345&vendorItemId=4822351124&traceid=V0-113-3f9859921993cf4c","categoryName":"헬스/건강식품","keyword":"헬스/건강식품","rank":60,"isRocket":true,"isFreeShipping":false},{"productId":67557481,"productName":"종근당 칼슘 앤 마그네슘 비타민D 아연, 180정, 2개","productPrice":19760,"productImage":"https://static.coupangcdn.com/image/retail/images/602700018077660-512744b5-e6f1-4c49-958b-a8a45720c2dc.jpg","productUrl":"https://link.coupang.com/re/AFFSDP?lptag=AF9416635&pageKey=67557481&itemId=537226687&vendorItemId=4402720917&traceid=V0-113-bb53c33c877ffe45","categoryName":"헬스/건강식품","keyword":"헬스/건강식품","rank":61,"isRocket":true,"isFreeShipping":false},{"productId":6074013700,"productName":"코멧 KF94 보건마스크 새부리형 2단접이 대형, 5개입, 20개, 화이트","productPrice":19900,"productImage":"https://static.coupangcdn.com/image/retail/images/9178931526940208-c5f69b1d-e93a-4b4c-ba4c-8531417a4b47.jpg","productUrl":"https://link.coupang.com/re/AFFSDP?lptag=AF9416635&pageKey=6074013700&itemId=11226775482&vendorItemId=78504142111&traceid=V0-113-afc979c267bf6ed8","categoryName":"헬스/건강식품","keyword":"헬스/건강식품","rank":62,"isRocket":true,"isFreeShipping":false},{"productId":2358504828,"productName":"아이시스 8.0 생수, 2L, 24개","productPrice":15500,"productImage":"https://static.coupangcdn.com/image/retail/images/2020/11/06/11/6/61e77ca7-24de-47ef-b3cd-ebbfcae797b6.jpg","productUrl":"https://link.coupang.com/re/AFFSDP?lptag=AF9416635&pageKey=2358504828&itemId=4093405747&vendorItemId=72077387727&traceid=V0-113-7098909a9ad16d10","categoryName":"헬스/건강식품","keyword":"헬스/건강식품","rank":63,"isRocket":true,"isFreeShipping":false},{"productId":5491433779,"productName":"얼라이브 원스 데일리 포맨 멀티 비타민, 60정, 1개","productPrice":19500,"productImage":"https://static.coupangcdn.com/image/retail/images/82209583454962-715fc46b-5d61-40c0-8298-6860348638d3.png","productUrl":"https://link.coupang.com/re/AFFSDP?lptag=AF9416635&pageKey=5491433779&itemId=8502454428&vendorItemId=3000065023&traceid=V0-113-fc8be80bda478b69","categoryName":"헬스/건강식품","keyword":"헬스/건강식품","rank":64,"isRocket":true,"isFreeShipping":false},{"productId":1766640060,"productName":"곰곰 아삭한 그린 채소믹스 더블팩, 300g, 2개","productPrice":7450,"productImage":"https://static.coupangcdn.com/image/retail/images/23695301232595-e7b1b746-c12b-43fe-a24b-52b34db2839a.jpg","productUrl":"https://link.coupang.com/re/AFFSDP?lptag=AF9416635&pageKey=1766640060&itemId=3008229372&vendorItemId=70996442880&traceid=V0-113-072b4ffefc3f2f31","categoryName":"헬스/건강식품","keyword":"헬스/건강식품","rank":65,"isRocket":true,"isFreeShipping":false},{"productId":162959907,"productName":"호주산 소고기 모듬 국거리용 (냉장), 300g, 1개","productPrice":9600,"productImage":"https://static.coupangcdn.com/image/retail/images/4185898174692713-a764b4df-be84-4b95-bd40-a598e794aa12.jpg","productUrl":"https://link.coupang.com/re/AFFSDP?lptag=AF9416635&pageKey=162959907&itemId=467994843&vendorItemId=4167074729&traceid=V0-113-3df07ff70df8bfb6","categoryName":"헬스/건강식품","keyword":"헬스/건강식품","rank":66,"isRocket":true,"isFreeShipping":false},{"productId":214927173,"productName":"스미후루 스위트마운틴 바나나, 1.5kg내외, 1개","productPrice":6900,"productImage":"https://static.coupangcdn.com/image/retail/images/2019/04/26/17/8/858747c2-5449-4e2d-96b0-0d8ee1aa26c8.jpg","productUrl":"https://link.coupang.com/re/AFFSDP?lptag=AF9416635&pageKey=214927173&itemId=656424375&vendorItemId=4702108403&traceid=V0-113-5b28114aa19f1959","categoryName":"헬스/건강식품","keyword":"헬스/건강식품","rank":67,"isRocket":true,"isFreeShipping":false},{"productId":218742759,"productName":"웅진 하늘보리, 500ml, 24개","productPrice":13470,"productImage":"https://static.coupangcdn.com/image/product/image/vendoritem/2018/10/30/3051369121/0786926d-42fc-4ce0-abc0-72a521d447a9.jpg","productUrl":"https://link.coupang.com/re/AFFSDP?lptag=AF9416635&pageKey=218742759&itemId=34689229&vendorItemId=3051369121&traceid=V0-113-1481d72ec858db12","categoryName":"헬스/건강식품","keyword":"헬스/건강식품","rank":68,"isRocket":true,"isFreeShipping":false},{"productId":5580385248,"productName":"트레비 레몬 ECO 탄산수, 20개, 350ml","productPrice":10500,"productImage":"https://static.coupangcdn.com/image/retail/images/2673845445133935-ac6fa79a-fb7f-407e-a09c-ea7c9d08bfad.jpg","productUrl":"https://link.coupang.com/re/AFFSDP?lptag=AF9416635&pageKey=5580385248&itemId=8916449539&vendorItemId=76203054605&traceid=V0-113-223243da4c3c3830","categoryName":"헬스/건강식품","keyword":"헬스/건강식품","rank":69,"isRocket":true,"isFreeShipping":false},{"productId":2000584181,"productName":"아이시스 ECO 생수, 500ml, 40개","productPrice":11070,"productImage":"https://static.coupangcdn.com/image/retail/images/2020/08/24/15/1/70b0a179-6e35-4350-a8a6-b33266021b05.jpg","productUrl":"https://link.coupang.com/re/AFFSDP?lptag=AF9416635&pageKey=2000584181&itemId=9522385194&vendorItemId=71390979598&traceid=V0-113-7dc38a820918a24c","categoryName":"헬스/건강식품","keyword":"헬스/건강식품","rank":70,"isRocket":true,"isFreeShipping":false},{"productId":4869850561,"productName":"탐사 KF94 방역마스크 새부리형 2단접이 대형 50p (5매입 지퍼백 10개), 1개, 블랙","productPrice":17290,"productImage":"https://static.coupangcdn.com/image/retail/images/510936081509516-db3b35e6-e087-40ca-86ae-11563fdbe477.jpg","productUrl":"https://link.coupang.com/re/AFFSDP?lptag=AF9416635&pageKey=4869850561&itemId=6326081634&vendorItemId=73621505004&traceid=V0-113-04a3c4cdbe40e291","categoryName":"헬스/건강식품","keyword":"헬스/건강식품","rank":71,"isRocket":true,"isFreeShipping":false},{"productId":213797578,"productName":"모아미트 보리먹인 암퇘지 삼겹살 구이용 (냉장), 1kg, 1개","productPrice":20400,"productImage":"https://static.coupangcdn.com/image/retail/images/168892469154268-66176503-773e-43a4-975b-b176628c7324.jpg","productUrl":"https://link.coupang.com/re/AFFSDP?lptag=AF9416635&pageKey=213797578&itemId=649012177&vendorItemId=4687386308&traceid=V0-113-005a992debc8f19b","categoryName":"헬스/건강식품","keyword":"헬스/건강식품","rank":72,"isRocket":true,"isFreeShipping":false},{"productId":27613130,"productName":"탐사수, 330ml, 40개","productPrice":8090,"productImage":"https://static.coupangcdn.com/image/retail/images/779805884382-7197c9ea-06c2-447e-afc8-87ad4aef22aa.jpg","productUrl":"https://link.coupang.com/re/AFFSDP?lptag=AF9416635&pageKey=27613130&itemId=367921095&vendorItemId=3893406408&traceid=V0-113-b860fd2b23f3b002","categoryName":"헬스/건강식품","keyword":"헬스/건강식품","rank":73,"isRocket":true,"isFreeShipping":false},{"productId":111215672,"productName":"돈마루 한돈 앞다리 찌개용 (냉장), 500g, 1개","productPrice":8830,"productImage":"https://static.coupangcdn.com/image/retail/images/7214764443811422-bf9ff8ee-0224-4ce1-a32a-140d4110ef22.jpg","productUrl":"https://link.coupang.com/re/AFFSDP?lptag=AF9416635&pageKey=111215672&itemId=334996741&vendorItemId=3822003808&traceid=V0-113-acacb8314ba2ebdc","categoryName":"헬스/건강식품","keyword":"헬스/건강식품","rank":74,"isRocket":true,"isFreeShipping":false},{"productId":280608869,"productName":"풀무원 한끼 연두부 + 오리엔탈 유자 소스 6개입, 110g, 1세트","productPrice":8340,"productImage":"https://static.coupangcdn.com/image/retail/images/252624363366959-53dedde6-6cbd-4d98-b6c5-cb59d41da4dc.JPG","productUrl":"https://link.coupang.com/re/AFFSDP?lptag=AF9416635&pageKey=280608869&itemId=890782153&vendorItemId=5241766159&traceid=V0-113-db94cfea3dea59f1","categoryName":"헬스/건강식품","keyword":"헬스/건강식품","rank":75,"isRocket":true,"isFreeShipping":false},{"productId":4869850477,"productName":"탐사 KF94 방역마스크 새부리형 2단접이 50p (5매입 지퍼백 10개), 중형","productPrice":15290,"productImage":"https://static.coupangcdn.com/image/retail/images/3499614165167651-eea8f027-9f43-47e4-a276-3573b2c54b44.jpg","productUrl":"https://link.coupang.com/re/AFFSDP?lptag=AF9416635&pageKey=4869850477&itemId=6326081418&vendorItemId=73621504959&traceid=V0-113-d0a99d01a9e6ff62","categoryName":"헬스/건강식품","keyword":"헬스/건강식품","rank":76,"isRocket":true,"isFreeShipping":false},{"productId":1628662667,"productName":"하림 닭볶음탕용 닭고기 2개입 (냉장), 2000g, 1개","productPrice":9900,"productImage":"https://static.coupangcdn.com/image/retail/images/2021/06/30/19/4/f078a61b-4112-4b5f-8b02-7bd1d26b089b.jpg","productUrl":"https://link.coupang.com/re/AFFSDP?lptag=AF9416635&pageKey=1628662667&itemId=11049206816&vendorItemId=78328735918&traceid=V0-113-468483cfb7c4b1f9","categoryName":"헬스/건강식품","keyword":"헬스/건강식품","rank":77,"isRocket":true,"isFreeShipping":false},{"productId":250855310,"productName":"마이산 맥반석 구운란 30구, 900g, 1개","productPrice":12900,"productImage":"https://static.coupangcdn.com/image/retail/images/2019/07/02/10/5/f59e3aac-d8db-4ff1-a6fc-1361ba5fcdd4.jpg","productUrl":"https://link.coupang.com/re/AFFSDP?lptag=AF9416635&pageKey=250855310&itemId=791998178&vendorItemId=5009820068&traceid=V0-113-b78886fa605e79a5","categoryName":"헬스/건강식품","keyword":"헬스/건강식품","rank":78,"isRocket":true,"isFreeShipping":false},{"productId":1628661260,"productName":"하림 닭다리살 정육 (냉장), 600g, 2개","productPrice":14900,"productImage":"https://static.coupangcdn.com/image/retail/images/2021/05/03/14/7/e7d2e9b2-6974-417d-be28-3f0a6b900724.jpg","productUrl":"https://link.coupang.com/re/AFFSDP?lptag=AF9416635&pageKey=1628661260&itemId=8501361562&vendorItemId=75788868706&traceid=V0-113-7b3dbf216ef87b5e","categoryName":"헬스/건강식품","keyword":"헬스/건강식품","rank":79,"isRocket":true,"isFreeShipping":false},{"productId":6035384827,"productName":"와이제이푸드 건강하게 구운란 60구, 2100g, 1개","productPrice":17900,"productImage":"https://static.coupangcdn.com/image/retail/images/2021/07/27/14/0/27479498-f178-4889-827e-3e80172f105e.jpg","productUrl":"https://link.coupang.com/re/AFFSDP?lptag=AF9416635&pageKey=6035384827&itemId=11017778900&vendorItemId=78297424955&traceid=V0-113-290637f983731e45","categoryName":"헬스/건강식품","keyword":"헬스/건강식품","rank":80,"isRocket":true,"isFreeShipping":false},{"productId":2305665305,"productName":"스마트클린 황사방역 마스크 대형 KF94 흰색, 1박스, 50매입","productPrice":17500,"productImage":"https://static.coupangcdn.com/image/vendor_inventory/2126/cb9edf8e9fed019548effbc2bc6ddcb69684d59e364a2c625d917c915b78.jpg","productUrl":"https://link.coupang.com/re/AFFSDP?lptag=AF9416635&pageKey=2305665305&itemId=3974059298&vendorItemId=73316296712&traceid=V0-113-dbaa1119bcab4577","categoryName":"헬스/건강식품","keyword":"헬스/건강식품","rank":81,"isRocket":false,"isFreeShipping":false},{"productId":1336170156,"productName":"곰곰 국내산 깐마늘, 1kg, 1개","productPrice":10900,"productImage":"https://static.coupangcdn.com/image/retail/images/99369610365617-a691e2f7-8e86-4a2b-8cd3-8ad3fa85d6a8.jpg","productUrl":"https://link.coupang.com/re/AFFSDP?lptag=AF9416635&pageKey=1336170156&itemId=3845019360&vendorItemId=71829825174&traceid=V0-113-41178acb99804098","categoryName":"헬스/건강식품","keyword":"헬스/건강식품","rank":82,"isRocket":true,"isFreeShipping":false},{"productId":346765263,"productName":"곰곰 오리지날 닭가슴살 슬라이스 (냉동), 120g, 10개입","productPrice":15990,"productImage":"https://static.coupangcdn.com/image/retail/images/10783468200809103-aeb34e31-6468-400d-ac4b-965e12c884ef.jpg","productUrl":"https://link.coupang.com/re/AFFSDP?lptag=AF9416635&pageKey=346765263&itemId=6256269216&vendorItemId=73551976156&traceid=V0-113-7489f86ebb2221fe","categoryName":"헬스/건강식품","keyword":"헬스/건강식품","rank":83,"isRocket":true,"isFreeShipping":false},{"productId":218742759,"productName":"웅진 하늘보리, 500ml, 20개","productPrice":11440,"productImage":"https://static.coupangcdn.com/image/product/image/vendoritem/2018/11/22/3904133275/bbf5838a-f88c-4b39-9ffc-d1c64d79ec97.jpg","productUrl":"https://link.coupang.com/re/AFFSDP?lptag=AF9416635&pageKey=218742759&itemId=373049219&vendorItemId=3904133275&traceid=V0-113-1481d72ec858db12","categoryName":"헬스/건강식품","keyword":"헬스/건강식품","rank":84,"isRocket":true,"isFreeShipping":false},{"productId":5409105210,"productName":"에어데이즈 새부리형 마스크 C타입 대형 블랙 KF94, 1개입, 50개","productPrice":25590,"productImage":"https://static.coupangcdn.com/image/vendor_inventory/031d/da6d7380464be78fedfb277fff82a1613a0571efe8b60aa05fdbb3025606.png","productUrl":"https://link.coupang.com/re/AFFSDP?lptag=AF9416635&pageKey=5409105210&itemId=11913025575&vendorItemId=79185924380&traceid=V0-113-a5e16e551b5adf5e","categoryName":"헬스/건강식품","keyword":"헬스/건강식품","rank":85,"isRocket":false,"isFreeShipping":false},{"productId":1357560685,"productName":"아워홈 지리산수 핑크, 500ml, 60개","productPrice":11940,"productImage":"https://static.coupangcdn.com/image/retail/images/2020/07/13/17/9/cec713ed-11c3-47c5-ad86-da55789c5923.jpg","productUrl":"https://link.coupang.com/re/AFFSDP?lptag=AF9416635&pageKey=1357560685&itemId=3091525954&vendorItemId=71079354840&traceid=V0-113-fafe80139f625949","categoryName":"헬스/건강식품","keyword":"헬스/건강식품","rank":86,"isRocket":true,"isFreeShipping":false},{"productId":327206043,"productName":"충남세도 GAP 인증 대추방울토마토, 1kg, 1박스","productPrice":11700,"productImage":"https://static.coupangcdn.com/image/retail/images/2019/10/29/12/2/2b6c8fbb-106d-4732-b093-69cb4eeb6c70.jpg","productUrl":"https://link.coupang.com/re/AFFSDP?lptag=AF9416635&pageKey=327206043&itemId=1046983315&vendorItemId=5510129601&traceid=V0-113-f56f0587f172d8a3","categoryName":"헬스/건강식품","keyword":"헬스/건강식품","rank":87,"isRocket":true,"isFreeShipping":false},{"productId":1519330646,"productName":"햇살닭 저염훈제닭가슴살 플러스 (냉동), 100g, 10팩","productPrice":15250,"productImage":"https://static.coupangcdn.com/image/retail/images/2020/04/28/11/5/0fa77540-d4d2-4b73-8236-256c1874911f.jpg","productUrl":"https://link.coupang.com/re/AFFSDP?lptag=AF9416635&pageKey=1519330646&itemId=2607093811&vendorItemId=70598215704&traceid=V0-113-5265f6887227aec7","categoryName":"헬스/건강식품","keyword":"헬스/건강식품","rank":88,"isRocket":true,"isFreeShipping":false},{"productId":5423363776,"productName":"무항생제 인증 자연 그대로 신선한 하얀계란 대란 30구, 1560g, 1개","productPrice":8590,"productImage":"https://static.coupangcdn.com/image/retail/images/258581985118769-0746f4d5-5bd4-4de2-ab2a-5edc7aea4e10.jpg","productUrl":"https://link.coupang.com/re/AFFSDP?lptag=AF9416635&pageKey=5423363776&itemId=8196138572&vendorItemId=75484248826&traceid=V0-113-e1b6df1ae129ebe0","categoryName":"헬스/건강식품","keyword":"헬스/건강식품","rank":89,"isRocket":true,"isFreeShipping":false},{"productId":129241540,"productName":"동원에프앤비 비엔나소시지, 1kg, 1개","productPrice":10150,"productImage":"https://static.coupangcdn.com/image/retail/images/5120279096368072-77e802a9-0ab5-427d-9086-2611234d4624.jpg","productUrl":"https://link.coupang.com/re/AFFSDP?lptag=AF9416635&pageKey=129241540&itemId=380700176&vendorItemId=3922487803&traceid=V0-113-e8496a5d7444b9a8","categoryName":"헬스/건강식품","keyword":"헬스/건강식품","rank":90,"isRocket":true,"isFreeShipping":false},{"productId":6098365781,"productName":"락토핏 종근당건강 생유산균 골드 80, 160g, 1개","productPrice":19500,"productImage":"https://static.coupangcdn.com/image/retail/images/2981935313096180-11ae8543-dd0e-4b44-87c3-29ca3f9ce801.jpg","productUrl":"https://link.coupang.com/re/AFFSDP?lptag=AF9416635&pageKey=6098365781&itemId=3972669011&vendorItemId=4637889550&traceid=V0-113-c695d42f1e2a91ac","categoryName":"헬스/건강식품","keyword":"헬스/건강식품","rank":91,"isRocket":true,"isFreeShipping":false},{"productId":1816561336,"productName":"아워홈 지리산수, 2L, 18개","productPrice":9450,"productImage":"https://static.coupangcdn.com/image/retail/images/2020/07/13/17/2/048e12b7-6381-45e0-a6dc-4c64c444d196.jpg","productUrl":"https://link.coupang.com/re/AFFSDP?lptag=AF9416635&pageKey=1816561336&itemId=3091525781&vendorItemId=71079354713&traceid=V0-113-f32427b2d7c00ef5","categoryName":"헬스/건강식품","keyword":"헬스/건강식품","rank":92,"isRocket":true,"isFreeShipping":false},{"productId":1354181605,"productName":"곰곰 맥반석 구운란, 35g, 30구","productPrice":11890,"productImage":"https://static.coupangcdn.com/image/retail/images/31554486893621-a72fd033-931b-4a97-b3d6-3b0f477e28c3.jpg","productUrl":"https://link.coupang.com/re/AFFSDP?lptag=AF9416635&pageKey=1354181605&itemId=2382768229&vendorItemId=70378249265&traceid=V0-113-e7ba97ac615c407c","categoryName":"헬스/건강식품","keyword":"헬스/건강식품","rank":93,"isRocket":true,"isFreeShipping":false},{"productId":4683535861,"productName":"몽베스트 생수, 1L, 36개","productPrice":16880,"productImage":"https://static.coupangcdn.com/image/retail/images/2021/09/16/10/8/ee19302b-3ddf-4a81-a848-877629475817.jpg","productUrl":"https://link.coupang.com/re/AFFSDP?lptag=AF9416635&pageKey=4683535861&itemId=3106292726&vendorItemId=78555746509&traceid=V0-113-50ccda1736b1e161","categoryName":"헬스/건강식품","keyword":"헬스/건강식품","rank":94,"isRocket":true,"isFreeShipping":false},{"productId":187542484,"productName":"코멧 하이드로콜로이드 스팟패치 원형, 120매입, 1개","productPrice":8260,"productImage":"https://static.coupangcdn.com/image/product/image/vendoritem/2019/07/01/4399050496/eac79d6a-5d51-41fa-b7be-11e01e77aacd.jpg","productUrl":"https://link.coupang.com/re/AFFSDP?lptag=AF9416635&pageKey=187542484&itemId=536021148&vendorItemId=4399050496&traceid=V0-113-0cde81e1bf3322ce","categoryName":"헬스/건강식품","keyword":"헬스/건강식품","rank":95,"isRocket":true,"isFreeShipping":false}]}